fusiondirectory_api/__init__.py
fusiondirectory_api/fusiondirectory_api.py
fusiondirectory_api-0.0.8.dist-info/LICENSE
fusiondirectory_api-0.0.8.dist-info/METADATA
fusiondirectory_api-0.0.8.dist-info/WHEEL
fusiondirectory_api-0.0.8.dist-info/top_level.txt
fusiondirectory_api-0.0.8.dist-info/RECORD
